tests/__init__.py
tests/conftest.py
tests/test_data.py
tests/test_distance.py
tests/test_lenses.py
tests/test_load_artifact.py
tests/test_model_surgery.py
tests/test_stats.py
tests/test_subspaces.py
tests/test_unembed.py
tests/test_utils.py
tests/scripts/__init__.py
tests/scripts/test_integration.py
tuned_lens/__init__.py
tuned_lens/__main__.py
tuned_lens/data.py
tuned_lens/load_artifacts.py
tuned_lens/model_surgery.py
tuned_lens/utils.py
tuned_lens/causal/__init__.py
tuned_lens/causal/ablation.py
tuned_lens/causal/subspaces.py
tuned_lens/causal/utils.py
tuned_lens/nn/__init__.py
tuned_lens/nn/lenses.py
tuned_lens/nn/unembed.py
tuned_lens/plotting/__init__.py
tuned_lens/plotting/prediction_trajectory.py
tuned_lens/plotting/token_formatter.py
tuned_lens/plotting/trajectory_plotting.py
tuned_lens/scripts/__init__.py
tuned_lens/scripts/eval_loop.py
tuned_lens/scripts/ingredients.py
tuned_lens/scripts/train_loop.py
tuned_lens/stats/__init__.py
tuned_lens/stats/distance.py
tuned_lens/stats/logit_stats.py
tuned_lens-0.2.0.dist-info/LICENSE
tuned_lens-0.2.0.dist-info/METADATA
tuned_lens-0.2.0.dist-info/WHEEL
tuned_lens-0.2.0.dist-info/entry_points.txt
tuned_lens-0.2.0.dist-info/top_level.txt
tuned_lens-0.2.0.dist-info/RECORD
