Metadata-Version: 2.1
Name: tuned-lens
Version: 0.2.0
Summary: Tools for understanding how transformer predictions are built layer-by-layer
License: MIT License
Keywords: nlp,interpretability,language-models,explainable-ai
Requires-Python: >=3.9
License-File: LICENSE
Requires-Dist: accelerate
Requires-Dist: datasets
Requires-Dist: plotly (>=5.13.1)
Requires-Dist: torchdata (>=0.6.0)
Requires-Dist: torch (>=1.13.0)
Requires-Dist: transformers (>=4.28.1)
Requires-Dist: huggingface-hub (>=0.12.1)
Requires-Dist: simple-parsing (>=0.1.1)
Requires-Dist: flatten-dict (>=0.4.1)
Requires-Dist: wandb (>=0.15.0)
Provides-Extra: 8bit
Requires-Dist: bitsandbytes ; extra == '8bit'
Provides-Extra: dev
Requires-Dist: pre-commit ; extra == 'dev'
Requires-Dist: bump2version ; extra == 'dev'
Requires-Dist: pytest-skip-slow ; extra == 'dev'
Requires-Dist: pytest ; extra == 'dev'
Provides-Extra: docs
Requires-Dist: furo ; extra == 'docs'
Requires-Dist: myst-parser ; extra == 'docs'
Requires-Dist: sphinx ; extra == 'docs'
Requires-Dist: sphinx-autodoc-typehints ; extra == 'docs'
Requires-Dist: sphinx-rtd-theme ; extra == 'docs'
Requires-Dist: nbsphinx ; extra == 'docs'
Provides-Extra: notebooks
Requires-Dist: ipywidgets ; extra == 'notebooks'
Provides-Extra: slow_tokenizers
Requires-Dist: sentencepiece (>=0.1.99) ; extra == 'slow_tokenizers'
Provides-Extra: test
Requires-Dist: sentencepiece (>=0.1.99) ; extra == 'test'
Requires-Dist: transformer-lens (>=1.2.2) ; extra == 'test'
Requires-Dist: pytest-skip-slow ; extra == 'test'
Requires-Dist: pytest-cov ; extra == 'test'
Requires-Dist: nbmake ; extra == 'test'
Requires-Dist: pytest ; extra == 'test'
Requires-Dist: mock ; extra == 'test'
Provides-Extra: transformer_lens
Requires-Dist: transformer-lens (>=1.2.2) ; extra == 'transformer_lens'
